README.rst
setup.py
wunderpy/__init__.py
wunderpy.egg-info/PKG-INFO
wunderpy.egg-info/SOURCES.txt
wunderpy.egg-info/dependency_links.txt
wunderpy.egg-info/entry_points.txt
wunderpy.egg-info/requires.txt
wunderpy.egg-info/top_level.txt
wunderpy/api/__init__.py
wunderpy/api/calls.py
wunderpy/api/client.py
wunderpy/cli/__init__.py
wunderpy/cli/colors.py
wunderpy/cli/main.py
wunderpy/cli/storage.py
wunderpy/wunderlist/__init__.py
wunderpy/wunderlist/task.py
wunderpy/wunderlist/task_list.py
wunderpy/wunderlist/wunderlist.py