Metadata-Version: 1.1
Name: wunderpy
Version: 0.2.2
Summary: An experimental wrapper for the Wunderlist 2 API
Home-page: https://github.com/bsmt/wunderpy
Author: bsmt
Author-email: bsmt@bsmt.me
License: MIT
Platform: UNKNOWN
Classifier: Development Status :: 4 - Beta
Classifier: License :: OSI Approved :: MIT License
Classifier: Intended Audience :: Developers
Classifier: Natural Language :: English
Classifier: Programming Language :: Python
Classifier: Programming Language :: Python :: 2.7
Classifier: Programming Language :: Python :: 3
Classifier: Programming Language :: Python :: 3.3
Classifier: Topic :: Utilities
Classifier: Topic :: Documentation
Classifier: Environment :: Console
